scrapyd_website/__init__.py
scrapyd_website/website.py
scrapyd_website/templates/home.html
scrapyd_web-0.0.2.dist-info/LICENSE
scrapyd_web-0.0.2.dist-info/METADATA
scrapyd_web-0.0.2.dist-info/WHEEL
scrapyd_web-0.0.2.dist-info/top_level.txt
scrapyd_web-0.0.2.dist-info/RECORD
