Metadata-Version: 2.1
Name: scrapyd-web
Version: 0.0.2
Summary: scrapyd template customization
Home-page: https://github.com/serbernar/scrapyd-website
Author: Sergey Berebko
Author-email: serbernar1@gmail.com
License: MIT
Platform: UNKNOWN
Classifier: License :: OSI Approved :: MIT License
Classifier: Programming Language :: Python
Classifier: Programming Language :: Python :: 3
Classifier: Programming Language :: Python :: 3.6
Classifier: Programming Language :: Python :: Implementation :: CPython
Classifier: Programming Language :: Python :: Implementation :: PyPy
Requires-Python: >=3.4.0
Requires-Dist: scrapyd (>=1.2.0)
